Metadata-Version: 2.1
Name: EntropySGD
Version: 1.2.1
Summary: Entropy SGD optimizer
Home-page: https://github.com/steph1793/EntropySGD
Author: David Stephane Belemkoabga
Author-email: bdavidstephane@hotmail.com
License: MIT
Platform: UNKNOWN
Classifier: Programming Language :: Python :: 3
Classifier: License :: OSI Approved :: MIT License
Classifier: Operating System :: OS Independent
Requires-Python: >=3.6
